setup.py
django_polarize.egg-info/PKG-INFO
django_polarize.egg-info/SOURCES.txt
django_polarize.egg-info/dependency_links.txt
django_polarize.egg-info/requires.txt
django_polarize.egg-info/top_level.txt
polarize/__init__.py
polarize/model_mixins.py
polarize/models.py
polarize/migrations/0001_initial.py
polarize/migrations/__init__.py