Metadata-Version: 1.0
Name: django-polarize
Version: 0.1.0
Summary: Generic ratings app for Django
Home-page: https://github.com/hzy/django-polarize
Author: Jacob Haslehurst
Author-email: jacob@haslehurst.net
License: UNKNOWN
Platform: UNKNOWN
